open_browser.py
open_browser-0.2.0.dist-info/DESCRIPTION.rst
open_browser-0.2.0.dist-info/METADATA
open_browser-0.2.0.dist-info/RECORD
open_browser-0.2.0.dist-info/WHEEL
open_browser-0.2.0.dist-info/entry_points.txt
open_browser-0.2.0.dist-info/metadata.json
open_browser-0.2.0.dist-info/top_level.txt
