Metadata-Version: 2.0
Name: open-browser
Version: 0.2.0
Summary: Open url via the command line
Home-page: https://github.com/chenjiandongx/open-browser
Author: chenjiandongx
Author-email: chenjiandongx@qq.com
License: MIT
Platform: UNKNOWN
